eta_incerto/.DS_Store
eta_incerto/__init__.py
eta_incerto/analysis/__init__.py
eta_incerto/analysis/metrics.py
eta_incerto/analysis/sensitivity.py
eta_incerto/analysis/sensitivity_reporting.py
eta_incerto/config/__init__.py
eta_incerto/config/config.py
eta_incerto/config/config_algorithm.py
eta_incerto/config/config_analysis.py
eta_incerto/config/config_antifragile.py
eta_incerto/config/config_data.py
eta_incerto/config/config_doe.py
eta_incerto/config/config_evaluate.py
eta_incerto/config/config_investment.py
eta_incerto/config/config_paths.py
eta_incerto/config/config_pcetest.py
eta_incerto/config/config_plotting.py
eta_incerto/config/config_problem.py
eta_incerto/config/config_scenario.py
eta_incerto/config/config_series.py
eta_incerto/config/config_settings.py
eta_incerto/config/config_system.py
eta_incerto/config/config_termination.py
eta_incerto/config/registry.py
eta_incerto/core.py
eta_incerto/envs/__init__.py
eta_incerto/envs/antifragile.py
eta_incerto/envs/antifragile_vectorized.py
eta_incerto/envs/base.py
eta_incerto/envs/deterministic.py
eta_incerto/envs/deterministic_evaluation.py
eta_incerto/envs/doe.py
eta_incerto/envs/feasibility.py
eta_incerto/envs/model.py
eta_incerto/envs/pcetest.py
eta_incerto/envs/regret.py
eta_incerto/envs/regret_evaluation.py
eta_incerto/envs/robust.py
eta_incerto/envs/robust_evaluation.py
eta_incerto/envs/scenario.py
eta_incerto/envs/stochastic.py
eta_incerto/envs/stochastic_evaluation.py
eta_incerto/envs/utils.py
eta_incerto/periods/__init__.py
eta_incerto/periods/analysis_adapter.py
eta_incerto/periods/data_to_periods.py
eta_incerto/plotting/__init__.py
eta_incerto/plotting/dispatch.py
eta_incerto/plotting/doe_plotter.py
eta_incerto/plotting/pareto.py
eta_incerto/plotting/pce_rmse.py
eta_incerto/plotting/performance.py
eta_incerto/plotting/report.py
eta_incerto/plotting/scenario.py
eta_incerto/plotting/summary.py
eta_incerto/plotting/summary_template.py
eta_incerto/plotting/table.py
eta_incerto/plotting/topology.py
eta_incerto-1.0.1.dist-info/LICENSE
eta_incerto-1.0.1.dist-info/METADATA
eta_incerto-1.0.1.dist-info/WHEEL
eta_incerto-1.0.1.dist-info/RECORD
