Metadata-Version: 2.3
Name: eta-incerto
Version: 1.0.1
Summary: Library for modeling investment decisions under uncertainty
License: BSD-2-Clause License
Keywords: investment,uncertainty,modeling,robust,regret,stochastic
Author: Technical University of Darmstadt, Institute for Production Management, Technology and Machine Tools (PTW)
Author-email: m.frank@ptw.tu-darmstadt.de
Requires-Python: >=3.11, <3.13
Classifier: Development Status :: 4 - Beta
Classifier: Intended Audience :: Developers
Classifier: Intended Audience :: Manufacturing
Classifier: Intended Audience :: Science/Research
Classifier: License :: OSI Approved :: BSD License
Classifier: License :: Other/Proprietary License
Classifier: Operating System :: OS Independent
Classifier: Programming Language :: Python :: 3
Classifier: Programming Language :: Python :: 3.11
Classifier: Programming Language :: Python :: 3.12
Classifier: Topic :: Scientific/Engineering :: Artificial Intelligence
Requires-Dist: attrs (>=25.3.0,<26.0.0)
Requires-Dist: backports-datetime-fromisoformat (==2.0.0)
Requires-Dist: chaospy (>=4.3.20,<5.0.0)
Requires-Dist: eta-components (>=0.0.6,<0.0.7)
Requires-Dist: gurobipy (>=12.0.3,<13.0.0)
Requires-Dist: hplib (>=1.9,<2.0)
Requires-Dist: pyarrow (>=22.0.0,<23.0.0)
Requires-Dist: pydantic (>=2.11.7,<3.0.0)
Requires-Dist: pydot (>=4.0.1,<5.0.0)
Requires-Dist: pymoo (>=0.6.1.5,<0.7.0.0)
Requires-Dist: pyomo (>=6.9.2,<7.0.0)
Requires-Dist: rheia (>=1.1.13,<2.0.0)
Requires-Dist: salib (>=1.5.2,<2.0.0)
Requires-Dist: seaborn (>=0.13.2,<0.14.0)
Requires-Dist: stable_baselines3 (>=2.1,<3.0)
Requires-Dist: tables (>=3.10.2,<4.0.0)
Requires-Dist: toml (>=0.10.2,<0.11.0)
Requires-Dist: tsam (>=2.3.9,<3.0.0)
Project-URL: Homepage, https://www.ptw.tu-darmstadt.de
